Metadata-Version: 2.4
Name: thermo_flux
Version: 0.0.1
Summary: Thermodynamic flux analysis
Author-email: Edward Smith <edward.smith@biology.ox.ac.uk>, Nathan Fargier <nathan.fargier@rug.nl>
License: GPL-3.0
Project-URL: Homepage, https://github.com/molecular-systems-biology/thermo-flux
Project-URL: Bug Tracker, https://github.com/molecular-systems-biology/thermo-flux/issues
Classifier: License :: OSI Approved :: GNU General Public License v3 (GPLv3)
Classifier: Programming Language :: Python :: 3
Requires-Python: ~=3.9
License-File: LICENSE
Requires-Dist: numpy>=1.13
Requires-Dist: h5py
Requires-Dist: openpyxl
Requires-Dist: cobra
Requires-Dist: pandas>=1.4.4
Requires-Dist: click
Requires-Dist: click-log
Requires-Dist: importlib-resources==5.10
Requires-Dist: periodictable
Requires-Dist: python-dateutil
Requires-Dist: requests
Requires-Dist: equilibrator-api>=0.4.7
Requires-Dist: component-contribution>=0.4.3
Requires-Dist: equilibrator-cache>=0.4.3
Requires-Dist: equilibrator-assets>=0.4.2
Requires-Dist: jupyter
Requires-Dist: matplotlib
Requires-Dist: seaborn
Dynamic: license-file
